idgenerator/__init__.py
idgenerator/src/__init__.py
idgenerator/src/idgenerator.py
idgenerator/src/utils.py
idgenerator/test/__init__.py
idgenerator/test/test_idgenerator.py
vanta_yc33317-0.0.1.dist-info/LICENSE
vanta_yc33317-0.0.1.dist-info/METADATA
vanta_yc33317-0.0.1.dist-info/WHEEL
vanta_yc33317-0.0.1.dist-info/top_level.txt
vanta_yc33317-0.0.1.dist-info/RECORD
