Metadata-Version: 2.1
Name: vanta-yc33317
Version: 0.0.1
Summary: Log-Table converter
Home-page: UNKNOWN
Author: YC33317
Author-email: yatipa.c@vanta-capital.com
License: MIT
Platform: UNKNOWN
Classifier: License :: OSI Approved :: MIT License
Classifier: Programming Language :: Python :: 3.10
Classifier: Operating System :: OS Independent
Requires-Python: ==3.8.10
Requires-Dist: bson (>=0.5.10)
Provides-Extra: dev
Requires-Dist: pytest (>=7.0) ; extra == 'dev'
Requires-Dist: twine (>=4.0.2) ; extra == 'dev'
